textual_image/__init__.py
textual_image/__main__.py
textual_image/_geometry.py
textual_image/_pixeldata.py
textual_image/_posix.py
textual_image/_sixel.py
textual_image/_terminal.py
textual_image/_utils.py
textual_image/_win32.py
textual_image/gracehopper.jpg
textual_image/py.typed
textual_image/demo/__init__.py
textual_image/demo/renderable.py
textual_image/demo/widget.py
textual_image/renderable/__init__.py
textual_image/renderable/_protocol.py
textual_image/renderable/halfcell.py
textual_image/renderable/sixel.py
textual_image/renderable/tgp.py
textual_image/renderable/unicode.py
textual_image/widget/__init__.py
textual_image/widget/_base.py
textual_image/widget/sixel.py
textual_image-0.8.5.dist-info/licenses/LICENSE.txt
textual_image-0.8.5.dist-info/METADATA
textual_image-0.8.5.dist-info/WHEEL
textual_image-0.8.5.dist-info/top_level.txt
textual_image-0.8.5.dist-info/RECORD
