Metadata-Version: 2.4
Name: textual-image
Version: 0.8.5
Summary: Render images via Kitty's Terminal Graphics Protocol with Rich and Textual
Author-email: Simon Hayessen <simon@lnqs.io>
Project-URL: Homepage, https://github.com/lnqs/textual-image
Project-URL: Documentation, https://github.com/lnqs/textual-image
Project-URL: Repository, https://github.com/lnqs/textual-image
Project-URL: Issues, https://github.com/lnqs/textual-image/issues
Classifier: Development Status :: 4 - Beta
Classifier: Intended Audience :: Developers
Classifier: Environment :: Console
Classifier: Topic :: Software Development :: Libraries
Classifier: Topic :: Software Development :: User Interfaces
Classifier: License :: OSI Approved :: GNU Library or Lesser General Public License (LGPL)
Classifier: License :: OSI Approved :: GNU Lesser General Public License v3 or later (LGPLv3+)
Classifier: Operating System :: POSIX :: Linux
Classifier: Programming Language :: Python :: 3
Classifier: Programming Language :: Python :: 3.10
Classifier: Programming Language :: Python :: 3.11
Classifier: Programming Language :: Python :: 3.12
Classifier: Programming Language :: Python :: 3.13
Classifier: Typing :: Typed
License-File: LICENSE.txt
Requires-Dist: pillow>=10.3.0
Requires-Dist: rich>=13.4.0
Provides-Extra: textual
Requires-Dist: textual>=0.68.0; extra == "textual"
Provides-Extra: dev
Requires-Dist: mypy; extra == "dev"
Requires-Dist: pytest; extra == "dev"
Requires-Dist: pytest-asyncio; extra == "dev"
Requires-Dist: pytest-cov; extra == "dev"
Requires-Dist: ruff; extra == "dev"
Requires-Dist: syrupy; extra == "dev"
Requires-Dist: tox; extra == "dev"
Requires-Dist: typing-extensions; extra == "dev"
Requires-Dist: typos; extra == "dev"
Dynamic: license-file
